esmpi/__init__.py
esmpi/cmaes_mpi.py
esmpi/es_mpi.py
esmpi/mpi_vecnormalize.py
esmpi/optimizers.py
esmpi-1.0.dist-info/LICENSE
esmpi-1.0.dist-info/METADATA
esmpi-1.0.dist-info/WHEEL
esmpi-1.0.dist-info/top_level.txt
esmpi-1.0.dist-info/RECORD
