Metadata-Version: 2.1
Name: esmpi
Version: 1.0
Summary: Collection of Evolution Strategies optimizers with native MPI parallelization.
Author: Giacomo Spigler <http://www.spigler.net/giacomo>
License: MIT License
Project-URL: Homepage, https://airlab-tilburg.github.io
Project-URL: GitHub, https://github.com/spiglerg/esmpi
Keywords: evolution strategies,cma-es,mpi,openai-es
Classifier: Programming Language :: Python :: 3
Classifier: License :: OSI Approved :: MIT License
Classifier: Operating System :: OS Independent
Requires-Python: >=3.7
License-File: LICENSE
Requires-Dist: torch
Requires-Dist: mpi4py
Provides-Extra: full
Requires-Dist: stable-baselines3 ; extra == 'full'
Requires-Dist: cmaes ; extra == 'full'
